ppauth_cli/__init__.py
ppauth_cli/__main__.py
ppauth_cli-0.1.3.dist-info/METADATA
ppauth_cli-0.1.3.dist-info/WHEEL
ppauth_cli-0.1.3.dist-info/entry_points.txt
ppauth_cli-0.1.3.dist-info/top_level.txt
ppauth_cli-0.1.3.dist-info/RECORD
