Metadata-Version: 2.4
Name: ppauth-cli
Version: 0.1.3
Summary: Command-line interface for ProxyAuth
Author: vBlackOut
License: Apache-2.0
Requires-Python: >=3.8
Requires-Dist: requests
Requires-Dist: qrcode
